<?xml version="1.0" encoding="utf-8"?>
<search>
  
  
  
  <entry>
    <title>冥冥之中 似有神助</title>
    <link href="/2023/11/23/forth-art/"/>
    <url>/2023/11/23/forth-art/</url>
    
    <content type="html"><![CDATA[<p>我曾經被女生幹過</p><p>讓我心靈受創</p><p>那天晚上</p><p>應該說凌晨一點</p><p>姊姊躺在沙發上看電視</p><p>丟了五十塊錢的銅板給我叫我跑腿買飲料</p><p>我一個人走到小七開冰箱拿了兩罐麥香奶茶</p><p>然後回來</p><p>經過一戶人家的騎樓</p><p>遇到一個漂亮妹子</p><p>她看起來好像是太妹</p><p>側坐在摩托車上 一手拿菸 一手點火</p><p>然後開始吞雲吐霧 抽了起來</p><p>三更半夜的 我帶著納悶的眼神 在想</p><p>為什麼她會流落街頭不回家??</p><p>突然太妹抬起頭來</p><p>跟我眼神交會 發現我在偷瞄她</p><p>她惡狠狠的嗆了一聲:“幹你娘!! 青殺小!!”</p><p>我肩膀一聳 嚇得兩旁口袋裡的飲料都掉在地上</p><p>我戰戰兢兢的 蹲下撿起</p><p>然後她緩緩走來 也跟著蹲下</p><p>伸出指頭端起我的下巴 又問:</p><p>“幹！啊不然哩係咧青殺小??”</p><p>我結結巴巴說:“沒有啊 我只是在想…只是在想…”</p><p>她問:“想殺小??”</p><p>我說:“我在想…天那麼黑 風那麼大 為什麼妳還不回家??”</p><p>聽完 她調開眼光 不經意流露出悲傷的神情</p><p>沒想我隨口一番話 竟觸動她的心事</p><p>我知道很多流落街頭的少女</p><p>都是被家庭拋棄 沒人關懷沒人愛</p><p>我也不知道該怎麼安慰她</p><p>只好顫著手 遞出飲料 說:“我請妳喝…”</p><p>太妹看了看 問我:“這是什麼??”</p><p>我說:“麥香奶茶”</p><p>聽完 她一掌往我頭上巴下去 罵:</p><p>“幹你沒錢是不是?? 怎麼買這麼便宜的??”</p><p>然後她開始搜我兩邊的口袋</p><p>結果只搜到三十塊錢的銅板 跟一張統一發票</p><p>她似乎不滿足 生氣了</p><p>太妹說:”幹你娘晚上不睡覺 在外面爬爬造</p><p>還買我最討厭的麥香奶茶 我看你是欠幹!!”</p><p>她一腳把我踢倒在地 然後順勢拖下我的褲子</p><p>撩開她的裙子 直接騎上來幹我</p><p>我的老二被緊緊吸進她的私處</p><p>說我沒有感覺 那是騙人的</p><p>但我咬著下唇 忍受屈辱 眼角流淚</p><p>我希望這種事情是男歡女愛 你情我願</p><p>而不是妳硬騎上來 強迫我接受</p><p>如果心靈無法契合 那只有肉體上的高潮</p><p>卻無法達到精神上的滿足</p><p>不要…不要…不要幹我…</p><p>我被女生幹了…而且感到矛盾的痛苦…</p><p>她只容許我輕聲的呻吟</p><p>這樣會使她感到些微的成就 證明自己的魅力</p><p>但我若再大聲一點 奔放情感 用力嘶吼</p><p>她就會毫不留情的 往我臉上揍下去</p><p>因為這是強姦 不是做愛 她要狠狠的幹死我…</p><p>她頂多才十五歲啊…</p><p>完事之後</p><p>她把我身上的三十塊錢跟統一發票搶走</p><p>警告我別在路上亂青人 因為很欠幹</p><p>我眼界迷濛 覺得自己好像是一隻性奴</p><p>雙腳疲軟 目送她離開</p><p>連她腳上穿什麼鞋 我都模模糊糊的看不清楚</p><p>她邊走邊說:”晚上不睡覺…外面爬爬造…</p><p>還喝我最討厭的麥香奶茶…會出事的唷…”</p><p>然後幽幽的嘆了口氣 消失在街角的另一頭</p><p>我站起身來</p><p>回去之後</p><p>打開門</p><p>姊姊問:“怎麼那麼久 是不是被車撞了??”</p><p>可是她轉眼看我一臉狼狽 全身汙泥</p><p>趕緊從沙發上跳起來 問:“怎麼啦??”</p><p>我衝上前去 緊緊抱住姊姊哭著說:</p><p>“我…我被強姦了!! 嗚嗚~~”</p><p>姊姊不敢相信 說:</p><p>“沒想到這世界上 會有人那麼不挑…”</p><p>我說:“而且她還把我的錢跟統一發票搶走 嗚嗚~~”</p><p>姊姊說:“不是你的 是我的 看你都迷糊了”</p><p>她扶著我 把我載去醫院驗傷 然後採集下體體液</p><p>可是竟然採集不到其他人的DNA</p><p>檢驗人員只看到一堆蝌蚪 還懷疑我說謊</p><p>但是姊姊相信我了 頻頻安慰我說:</p><p>“人沒事就好 反正你也不會懷孕…”</p><p>折騰了一晚 這時我們才打開兩罐麥香奶茶一起喝</p><p>後來</p><p>我不敢再經過同樣的一條路</p><p>我怕會想起當晚恐怖的回憶</p><p>但一個禮拜之後的一個晚上</p><p>應該說是凌晨</p><p>姊姊又想喝飲料了</p><p>她把我推出去 鼓勵我要克服心理的恐懼</p><p>勇敢的踏出去 早去早回</p><p>其實姊姊只想利用我 幫她跑腿買飲料</p><p>出門之後 我一路低頭 不敢亂看</p><p>直到我撞到人家的棚子</p><p>因為路上有人辦喪事 而棚子占了半邊馬路</p><p>被我直直撞上</p><p>我不經意的看了遺像一眼 卻赫然發現</p><p>遺像上的漂亮女孩 竟是當晚所遇見的太妹</p><p>門口有他們的家屬在摺紙蓮花</p><p>我拉了一條凳子坐下 也跟他們一起摺</p><p>他們覺得奇怪 問我是誰??</p><p>我抬起頭來 不自覺的流下眼淚 感到悲傷</p><p>我問:“這女孩是誰?? 她怎麼死的??”</p><p>一個老婦人哭哭啼啼的說:</p><p>“那是我的女兒 不愛念書 正在休學</p><p>有一天晚上不睡覺 被8+9約出去撒野</p><p>但騎車雙載 在半路遇到死亡車禍 撞電線桿死了”</p><p>我苦笑說:“想必是屁孩8+9 連駕照都沒有囉??”</p><p>老婦人卻搖搖頭 說:“是有駕照 但真正肇事的原因卻令人想不透…”</p><p>我問:“怎麼想不透??”</p><p>老婦人說:</p><p>“在現場發現一個被壓扁的鋁箔包</p><p>上面正巧是他們摩托車的輪胎痕</p><p>警察研判 是他們倆個騎車經過</p><p>剛好輾爆鋁箔包 蹦一聲 嚇到他們</p><p>所以才失去控制 撞到電線桿…”</p><p>我問:“鋁箔包…它的名字…叫什麼呢??”</p><p>老婦人說:“麥香奶茶”</p><p>聽完 我抖了一下 手上摺一半的紙蓮花掉在地上</p><p>我假裝從容 撿起紙蓮花 然後說:</p><p>“好一對亡命鴛鴦 能死在一塊也不枉了…”</p><p>老婦人嘆了口氣 說:</p><p>“可是八加九卻沒死 事發之後</p><p>畏罪潛逃 不見蹤影 不聞不問</p><p>我女兒白白丟掉一條性命…”</p><p>我狠狠捏緊手上的紙蓮花 罵:“幹!! 畜生!!”</p><p>老婦人說:”可是我後來夢到女兒</p><p>她告訴我 她在幽冥路上遇到另一個如意郎君</p><p>他瞄了我女兒一眼 女兒心裡覺得歡喜 就跟他相好</p><p>之後她就很安詳滿足的離開 去陰間報到了”</p><p>原來</p><p>那一天晚上 我遇到的太妹就是她</p><p>難怪那時候 我連她的腳都看不清楚</p><p>因為她根本就不是人</p><p>我拿出姊姊給我的五十塊錢銅板</p><p>裝進白包裡面 對著太妹遺像合十禱念</p><p>誰都不知道晚上不睡覺 外面爬爬造</p><p>會遇到什麼事情</p><p>不過那是一場很棒的夢遺</p><p>祝妳一路好走</p><p>這時</p><p>天花板突然飄下一張統一發票 拂過我的臉頰</p><p>睜眼一看 正是被她搶走的那張</p><p>後來兌獎</p><p>這張發票讓我中了兩百塊錢</p><p>冥冥之中</p><p>似有神助</p>]]></content>
    
    
    <categories>
      
      <category>6969</category>
      
    </categories>
    
    
    <tags>
      
      <tag>story</tag>
      
    </tags>
    
  </entry>
  
  
  
  <entry>
    <title>誰要買單</title>
    <link href="/2023/11/09/third-art/"/>
    <url>/2023/11/09/third-art/</url>
    
    <content type="html"><![CDATA[<ul><li>角色：醜男、女人、小白、店員</li><li>道具：手機 x 3</li></ul><p>（在咖啡廳外的餐桌）<br>（店員走向坐在餐桌旁的三位客人）</p><p>店員：您好，請問誰來買單？</p><p>醜男：誰弱誰買單（秀出手機畫面）我可是擁有「五星周伯通」的男人你買（看女人一眼）</p><p>女人：雖然我的 「獨孤求敗」 沒有進階到滿星， 但這裡（機掰臉）不是有個剛出新手村的小白嗎（看小白一眼）你來買！</p><p>小白：蛤？我可是有「滿星歐陽鋒」呢<br>（女人和醜男驚訝）</p><p>女人：你不是昨天晚上才下載的《新射雕群俠傳》嗎？</p><p>醜男：對啊對啊，怎麼這麼快拿到滿星英雄？</p><p>小白：對啊，我玩的是《新射雕群俠傳》啊！這遊戲爆率超高，我剛下載的遊戲，第一個十連抽就抽到了「歐陽鋒」，送的資源還特別多，一下子就到「滿星」了。我靠著他打贏了前期所有的副本</p><p>（結尾播放遊戲商提供影片）<br>希望能夠給大家帶來幫助ฅ’ω’ฅ</p>]]></content>
    
    
    
    <tags>
      
      <tag>story</tag>
      
    </tags>
    
  </entry>
  
  
  
  <entry>
    <title>堂堂阿宏</title>
    <link href="/2023/11/09/my-second-article/"/>
    <url>/2023/11/09/my-second-article/</url>
    
    <content type="html"><![CDATA[<p>跟大家分享個小故事</p><p>我那個時候還是個小處男高中生</p><p>某次跑去女朋友家玩</p><p>跟她的爸媽問候一下簡單聊兩句之後</p><p>就躲到女朋友的房間了</p><p>情侶間什麼不多 白癡的小動作最多</p><p>一開始只是打來打去</p><p>弄一弄到後來變成摔角比賽</p><p>最後我就把她壓在她的床上開始搔癢</p><p>我說:“認不認輸!!!”</p><p>她一邊大笑一邊掙扎:“哈哈哈…認輸認輸…不要在弄了…嗚嗚…”</p><p>看她被我弄的衣衫不整又被我壓在下面</p><p>害我心底的”火”有點上來了</p><p>我開始親她然後另一隻手揉她的小C奶</p><p>她微微呻吟:“恩…不要…在家裡不好…”</p><p>我沒等她講完就把嘴唇湊了上去</p><p>直接封住她的嘴巴XD</p><p>不知道是因為我挑逗技術高超</p><p>還是在家裡覺得羞恥的關係</p><p>今天的她好像真的很有感覺</p><p>她用氣音對我說:“我想要…”</p><p>總算解禁了 我整個興奮到不行</p><p>我一邊脫下褲子一邊又問:“真的可以嗎…”</p><p>她點點頭說:“恩…可是我也是第一次…你要小力一點…”</p><p>我用最快的速度把兩個人都扒個精光</p><p>女朋友的裸體之前有看過了所以衝擊還沒那麼大</p><p>真的插入倒是第一次 我整個硬到不行</p><p>我說:“轉過去 然後趴著背對我”</p><p>她乖乖的照做了 正準備要來個浪漫突刺的時候</p><p>她突然大喊:”等一下! “</p><p>幹! 嚇我一跳!</p><p>“怎麼了?” “你先關燈…” “又不是沒看過…” “關燈啦!”</p><p>我心不甘情不願的跑去關燈</p><p>回來就位之後 將肉棒對準感覺像是小穴的地方</p><p>慢慢的擠了進去 唔…好緊…</p><p>我問她說:“會痛嗎?”</p><p>她說:“咦?你進來了嗎?”</p><p>靠腰喔…這個緊到不行的包覆感是假的喔</p><p>我號稱新北第一大屌</p><p>看我如何把你構造改革</p><p>口是心非的女人…看我幹死妳!</p><p>我以狂風暴雨的攻勢擺動著公狗腰</p><p>“趴!趴!趴!”的聲音好大聲 猶如量子糾纏</p><p>黑暗中只聽到她慌慌張張的聲音:“等…等一下阿! 快停!”</p><p>現在才知道害怕太晚了!!! （卑鄙源之助</p><p>我要幹死妳!!!</p><p>100%馬力!!!</p><p>因為真的太緊了 沒多久我就射惹</p><p>完事後打開燈一看</p><p>女朋友她爸的褲子褪到膝蓋那裡趴在我女朋友身上</p><p>整個屁股都是洨…</p><p>原來是她爸拉完屎褲子還沒穿好就走出來聽到女兒房間內有騷動想進來一探究竟結果跌倒整個人趴在我女朋友身上暈了過去我女朋友以為是我也不以為意接著我趴到她爸身上捅到她爸的屁眼</p><p>督錯洞就算了…還督錯人的洞…</p><p>我趁她爸還沒清醒直接逃出了她家</p><p>後來我跟我女朋友因為其他事分手了 再也沒有聯絡</p><p>倒是她爸還常常來找我</p><p>還規定我不許再叫他”伯父”</p><p>要改叫他”糖糖阿宏”</p>]]></content>
    
    
    <categories>
      
      <category>8787</category>
      
    </categories>
    
    
    <tags>
      
      <tag>story</tag>
      
    </tags>
    
  </entry>
  
  
  
  <entry>
    <title>科學家的故事</title>
    <link href="/2023/11/09/my-first-article/"/>
    <url>/2023/11/09/my-first-article/</url>
    
    <content type="html"><![CDATA[<p>一群偉大的科學家死後在天堂裡玩藏貓貓，輪到愛因斯坦抓人，他數到100睜開眼睛，看到所有人都藏起來了，只見伏特趴在不遠處。</p><p>愛因斯坦走過去說：「伏特，我抓住你了。」</p><p>伏特說：「不，你沒有抓到我。」</p><p>愛因斯坦：「你不是伏特你是誰？」</p><p>伏特：「你看我身下是什麼？」</p><p>愛因斯坦低頭看到在伏特身下，居然是安培。</p><p>伏特：「我身下是安培，我倆就是伏特&#x2F;安培，所以你抓住的不是我，你抓住的是歐姆！」</p><p>愛因斯坦反應迅速，於是改口喊，歐姆，我抓住你了！」</p><p>可是伏特和安培畢竟是歐姆的好哥們，於是，伏特和安培一個魚躍站了起來，但是仍然緊緊抱在一起，愛因斯坦大惑。</p><p>他倆不緊不慢地說，現在，我們不再是歐姆，而是伏特×安培， 變成瓦特了。</p><p>愛因斯坦覺得有道理，於是喊：「那我終於抓到你了，瓦特！」</p><p>這時候，瓦特躲在角落裡慢慢悠悠地說：「你看他倆這樣抱著已經有好幾秒了，所以，你抓得不是瓦特，而是瓦特×秒，是焦耳啦。」</p><p>這時，他看到牛頓站在不遠處，愛因斯坦於是跑過去說：「牛頓，我抓住你了。」</p><p>牛頓：「不，你沒有抓到牛頓。」</p><p>愛因斯坦：「你不是牛頓你是誰？」</p><p>牛頓：「你看我腳下是什麼？」</p><p>愛因斯坦低頭看到牛頓站在一塊長寬都是一米的正方形的地板磚上，不解。<br>牛頓：「我腳下這是一平方米的方塊，我站在上面就是牛頓&#x2F;平方米，所以你抓住的不是牛頓，你抓住的是帕斯卡」</p><p>愛因斯坦倍受挫折，終於忍無可忍地爆發了，於是飛起一腳，踹在牛頓身上，把牛頓踹出了那塊一平米的地板磚，然後吼道：「說！你還敢說你是帕斯卡？」</p><p>牛頓慢慢地從地上爬起來，說：「不，我已經不是帕斯卡了，你剛剛讓我牛頓移動了一米的距離，所以，我現在也是焦耳了」</p><p>焦耳這次學聰明了，一把撲到了阿伏伽德羅在自己身下，說：“你看，我現在是J&#x2F;mol啦”，</p><p>正當愛因斯坦思考J&#x2F;mol是什麼東西的時候，亥姆霍茲和吉布斯這兩個自由能吵了起來，都說是對方。</p><p>為了不至於兩敗俱傷，他們一腳把開爾文踹到焦耳下面，把阿伏伽德羅頂了出來。</p><p>「看！」他倆說，「現在是J&#x2F;K，是熵啦，要抓就抓克勞修斯吧。」</p><p>遊戲繼續</p><p>這次是安培被愛因斯坦發現了，眼看安培就要被抓了。 安培順勢往地上一躺，伸直身體對站在身邊不遠處的愛因斯坦說：「等等，我在你站的地方產生了磁場。」</p><p>正當愛因斯坦在考慮該抓高斯還是特斯拉的時候，發現他倆一人找了一塊地板磚抱著說：「不麻煩你老了，我們現在是磁通量B·S，去找韋伯吧。」</p><p>等到愛因斯坦要抓住韋伯的時候，發現韋伯在做深蹲。</p><p>愛因斯坦問：「你幹嘛呢。」</p><p>韋伯回答說：「你沒看到我一會兒變大，一會兒變小，我在產生感應電動勢呢。」</p><p>這時伏特一下子慌了，一把抓住密立根的衣領，說：「你成天拿個油壺亂噴什麼。」</p><p>「測定元電荷。」密立根回答道。</p><p>「太好了！」伏特一把抱住密立根說，「從現在起，我們就是eV，也就是焦耳。」</p><p>「靠，今天是邪了門啦」焦耳嘀咕道，一把把赫茲壓在身下，說：「看，現在是E&#x2F;v，是普朗克啦。」</p><p>普朗克也不是好惹的，他突然發現遠處有個來自東方的老頭在地上寫下了22&#x2F;7和355&#x2F;113，很是得意，一打聽此人姓祖，心里大喜，急忙跑過去，把這兩個分數照抄了一遍，趴在這四個分數上面。 對剛氣喘噓噓趕來的愛因斯坦說：「看現在是h&#x2F;4pi,啦。」</p><p>「那又怎樣？」愛因斯坦問。</p><p>「是我的好哥們海森堡教我的，說這樣我就不是我了，有什麼事儘管找他。」</p><p>「好，那他在哪裡？」</p><p>「這個，還真說不准。」</p><p>愛因斯坦惱羞成怒，正準備對普朗克大打出手。 普朗克說：「等等，海森堡有個姓薛的好哥們，就躲在前面的箱子裡。」</p><p>「這個箱子連通風口都沒有，難道不會憋死嗎？」 愛因斯坦問。</p><p>「這個就得你親自去打開看看了。」</p>]]></content>
    
    
    <categories>
      
      <category>6969</category>
      
    </categories>
    
    
    <tags>
      
      <tag>story</tag>
      
    </tags>
    
  </entry>
  
  
  
  <entry>
    <title>Hello World</title>
    <link href="/2023/11/09/hello-world/"/>
    <url>/2023/11/09/hello-world/</url>
    
    <content type="html"><![CDATA[<p>Welcome to <a href="https://hexo.io/">Hexo</a>! This is your very first post. Check <a href="https://hexo.io/docs/">documentation</a> for more info. If you get any problems when using Hexo, you can find the answer in <a href="https://hexo.io/docs/troubleshooting.html">troubleshooting</a> or you can ask me on <a href="https://github.com/hexojs/hexo/issues">GitHub</a>.</p><h2 id="Quick-Start"><a href="#Quick-Start" class="headerlink" title="Quick Start"></a>Quick Start</h2><h3 id="Create-a-new-post"><a href="#Create-a-new-post" class="headerlink" title="Create a new post"></a>Create a new post</h3><figure class="highlight bash"><table><tr><td class="gutter"><pre><span class="line">1</span><br></pre></td><td class="code"><pre><code class="hljs bash">$ hexo new <span class="hljs-string">&quot;My New Post&quot;</span><br></code></pre></td></tr></table></figure><p>More info: <a href="https://hexo.io/docs/writing.html">Writing</a></p><h3 id="Run-server"><a href="#Run-server" class="headerlink" title="Run server"></a>Run server</h3><figure class="highlight bash"><table><tr><td class="gutter"><pre><span class="line">1</span><br></pre></td><td class="code"><pre><code class="hljs bash">$ hexo server<br></code></pre></td></tr></table></figure><p>More info: <a href="https://hexo.io/docs/server.html">Server</a></p><h3 id="Generate-static-files"><a href="#Generate-static-files" class="headerlink" title="Generate static files"></a>Generate static files</h3><figure class="highlight bash"><table><tr><td class="gutter"><pre><span class="line">1</span><br></pre></td><td class="code"><pre><code class="hljs bash">$ hexo generate<br></code></pre></td></tr></table></figure><p>More info: <a href="https://hexo.io/docs/generating.html">Generating</a></p><h3 id="Deploy-to-remote-sites"><a href="#Deploy-to-remote-sites" class="headerlink" title="Deploy to remote sites"></a>Deploy to remote sites</h3><figure class="highlight bash"><table><tr><td class="gutter"><pre><span class="line">1</span><br></pre></td><td class="code"><pre><code class="hljs bash">$ hexo deploy<br></code></pre></td></tr></table></figure><p>More info: <a href="https://hexo.io/docs/one-command-deployment.html">Deployment</a></p>]]></content>
    
    
    
    <tags>
      
      <tag>helloWorld</tag>
      
    </tags>
    
  </entry>
  
  
  
  
</search>
